dtdutils/__init__.py
dtdutils/people.py
dtdutils/world.py
dtdutils-0.1.dist-info/LICENSE.txt
dtdutils-0.1.dist-info/METADATA
dtdutils-0.1.dist-info/WHEEL
dtdutils-0.1.dist-info/top_level.txt
dtdutils-0.1.dist-info/RECORD
