Metadata-Version: 2.1
Name: dtdutils
Version: 0.1
Summary: Date, Time and Data utilities
Home-page: https://pypi.org/dtdutils
Author: Sandeep Singhal
Author-email: sandeep.singhal@gmail.com
License: UNKNOWN
Platform: UNKNOWN
Classifier: Programming Language :: Python :: 3
Classifier: License :: OSI Approved :: MIT License
Classifier: Operating System :: OS Independent
Requires-Python: >=3.6
